mzk_kramerius/__init__.py
mzk_kramerius/__main__.py
mzk_kramerius/parsers.py
mzk_kramerius/client/__init__.py
mzk_kramerius/client/base.py
mzk_kramerius/client/client.py
mzk_kramerius/client/items.py
mzk_kramerius/client/processing.py
mzk_kramerius/client/sdnnt.py
mzk_kramerius/client/search.py
mzk_kramerius/client/statistics.py
mzk_kramerius/datatypes/__init__.py
mzk_kramerius/datatypes/foxml.py
mzk_kramerius/datatypes/kramerius.py
mzk_kramerius/datatypes/licenses.py
mzk_kramerius/datatypes/processing.py
mzk_kramerius/datatypes/sdnnt.py
mzk_kramerius/datatypes/solr.py
mzk_kramerius/schemas/__init__.py
mzk_kramerius/schemas/document.py
mzk_kramerius/schemas/processing.py
mzk_kramerius/schemas/sdnnt.py
mzk_kramerius/schemas/search.py
mzk_kramerius-0.0.11.dist-info/METADATA
mzk_kramerius-0.0.11.dist-info/WHEEL
mzk_kramerius-0.0.11.dist-info/top_level.txt
mzk_kramerius-0.0.11.dist-info/RECORD
