Metadata-Version: 2.1
Name: mzk_kramerius
Version: 0.0.11
Summary: Partial Kramerius client for Kramerius version v7.0.39
Author: Robert Randiak
Author-email: randiak@mzk.com
Requires-Python: >=3.6
Requires-Dist: lxml
Requires-Dist: pydantic
Requires-Dist: requests
